[
  {
    "scenario_id": "valuation_scenario:GOOGL-2026Q3-BASE",
    "company_id": "company:US-GOOGL",
    "name": "2026 Q3 Base Case",
    "scenario_type": "base",
    "as_of_date": "2026-07-20",
    "description_zh_tw": "用於驗證估值架構的人工基準情境。",
    "research_period": "2026Q3",
    "revision": 1
  },
  {
    "scenario_id": "valuation_scenario:NVDA-2026Q3-BASE",
    "company_id": "company:US-NVDA",
    "research_period": "2026Q3",
    "revision": 1,
    "name": "2026 Q3 Base Case",
    "scenario_type": "base",
    "as_of_date": "2026-07-19",
    "description_zh_tw": "依使用者現有 structure.json 數值建立的多模型架構驗證情境。"
  }
]
